phantombuild/__init__.py
phantombuild/__main__.py
phantombuild/phantombuild.py
phantombuild/template.toml
phantombuild-0.2.0.dist-info/LICENSE
phantombuild-0.2.0.dist-info/METADATA
phantombuild-0.2.0.dist-info/WHEEL
phantombuild-0.2.0.dist-info/top_level.txt
phantombuild-0.2.0.dist-info/RECORD
