Metadata-Version: 2.1
Name: phantombuild
Version: 0.2.0
Summary: phantom-build is designed to make building Phantom easier
Home-page: http://github.com/dmentipl/phantom-build
Author: Daniel Mentiplay
License: MIT
Platform: UNKNOWN
Classifier: Development Status :: 5 - Production/Stable
Classifier: License :: OSI Approved :: MIT License
Classifier: Programming Language :: Python :: 3.7
Classifier: Programming Language :: Python :: 3.8
Classifier: Operating System :: OS Independent
Requires-Python: >=3.7
Requires-Dist: click
Requires-Dist: jinja2
Requires-Dist: tomlkit
